reclocks/__init__.py
reclocks/classes.py
reclocks/interfaces.py
reclocks/misc.py
reclocks-0.1.1.dist-info/METADATA
reclocks-0.1.1.dist-info/WHEEL
reclocks-0.1.1.dist-info/RECORD
