Metadata-Version: 2.3
Name: reclocks
Version: 0.1.1
Summary: Reverse entropy clocks traverse causality chains backward.
Project-URL: Homepage, https://github.com/k98kurz/reverse-entropy-clocks
Project-URL: Bug Tracker, https://github.com/k98kurz/reverse-entropy-clocks/issues
Author-email: k98kurz <k98kurz@gmail.com>
Classifier: Development Status :: 3 - Alpha
Classifier: License :: OSI Approved :: ISC License (ISCL)
Classifier: Operating System :: OS Independent
Classifier: Programming Language :: Python :: 3
Classifier: Topic :: Security :: Cryptography
Classifier: Topic :: System :: Networking :: Time Synchronization
Requires-Python: >=3.10
Requires-Dist: pynacl>=1.5.0
